{"modId":"miscutils","itemName":"itemDustSmallRhugnor","metadata":0,"displayName":"Small Pile of Rhugnor Dust","unlocalizedName":"item.itemDustSmallRhugnor","oreDictNames":["dustSmallRhugnor"],"id":"miscutils:itemDustSmallRhugnor:0","recipesAsOutput":[{"machine":"crafting_table","chunk":24,"index":66},{"machine":"gt.recipe.macerator","chunk":3,"index":129}],"recipesAsInput":[{"machine":"crafting_table","chunk":24,"index":65},{"machine":"crafting_table","chunk":24,"index":65},{"machine":"crafting_table","chunk":24,"index":65},{"machine":"crafting_table","chunk":24,"index":65},{"machine":"gt.recipe.packager","chunk":1,"index":444}]}