{"modId":"miscutils","itemName":"itemDustSmallGrisium","metadata":0,"displayName":"Small Pile of Grisium Dust","unlocalizedName":"item.itemDustSmallGrisium","oreDictNames":["dustSmallGrisium"],"id":"miscutils:itemDustSmallGrisium:0","recipesAsOutput":[{"machine":"crafting_table","chunk":23,"index":486},{"machine":"gt.recipe.lathe","chunk":0,"index":200},{"machine":"gt.recipe.macerator","chunk":2,"index":378},{"machine":"gt.recipe.macerator","chunk":2,"index":382},{"machine":"gt.recipe.macerator","chunk":2,"index":383}],"recipesAsInput":[{"machine":"crafting_table","chunk":23,"index":485},{"machine":"crafting_table","chunk":23,"index":485},{"machine":"crafting_table","chunk":23,"index":485},{"machine":"crafting_table","chunk":23,"index":485},{"machine":"gt.recipe.packager","chunk":1,"index":458}]}