{"modId":"ProjectBlue","itemName":"sprayCan","metadata":0,"displayName":"White Spray Paint","unlocalizedName":"item.gcewing_projectblue:sprayCan","nbt":"{color:0}","id":"ProjectBlue:sprayCan:0","recipesAsOutput":[{"machine":"crafting_table","chunk":94,"index":12},{"machine":"crafting_table","chunk":94,"index":13},{"machine":"crafting_table","chunk":94,"index":14},{"machine":"crafting_table","chunk":94,"index":15},{"machine":"crafting_table","chunk":94,"index":16},{"machine":"crafting_table","chunk":94,"index":17},{"machine":"crafting_table","chunk":94,"index":18},{"machine":"crafting_table","chunk":94,"index":19},{"machine":"crafting_table","chunk":94,"index":20},{"machine":"crafting_table","chunk":94,"index":21},{"machine":"crafting_table","chunk":94,"index":22},{"machine":"crafting_table","chunk":94,"index":23},{"machine":"crafting_table","chunk":94,"index":24},{"machine":"crafting_table","chunk":94,"index":25},{"machine":"crafting_table","chunk":94,"index":26},{"machine":"crafting_table","chunk":94,"index":27}],"recipesAsInput":[]}