{"modId":"Ztones","itemName":"tile.fortBlock","metadata":2,"displayName":"Fort ②","unlocalizedName":"tile.fortBlock. (2)","id":"Ztones:tile.fortBlock:2","recipesAsOutput":[{"machine":"crafting_table","chunk":0,"index":477},{"machine":"crafting_table","chunk":2,"index":55},{"machine":"crafting_table","chunk":3,"index":130},{"machine":"crafting_table","chunk":3,"index":133},{"machine":"crafting_table","chunk":4,"index":211},{"machine":"crafting_table","chunk":5,"index":289},{"machine":"crafting_table","chunk":6,"index":367},{"machine":"crafting_table","chunk":7,"index":445},{"machine":"crafting_table","chunk":9,"index":23},{"machine":"crafting_table","chunk":10,"index":101},{"machine":"crafting_table","chunk":11,"index":179},{"machine":"crafting_table","chunk":12,"index":257},{"machine":"crafting_table","chunk":13,"index":335},{"machine":"crafting_table","chunk":14,"index":413},{"machine":"crafting_table","chunk":15,"index":491},{"machine":"crafting_table","chunk":17,"index":69},{"machine":"crafting_table","chunk":18,"index":147},{"machine":"gt.recipe.assembler","chunk":1,"index":146}],"recipesAsInput":[{"machine":"crafting_table","chunk":3,"index":131},{"machine":"crafting_table","chunk":3,"index":132},{"machine":"crafting_table","chunk":3,"index":133},{"machine":"crafting_table","chunk":3,"index":134},{"machine":"crafting_table","chunk":3,"index":135},{"machine":"crafting_table","chunk":3,"index":136},{"machine":"crafting_table","chunk":3,"index":137},{"machine":"crafting_table","chunk":3,"index":138},{"machine":"crafting_table","chunk":3,"index":139},{"machine":"crafting_table","chunk":3,"index":140},{"machine":"crafting_table","chunk":3,"index":141},{"machine":"crafting_table","chunk":3,"index":142},{"machine":"crafting_table","chunk":3,"index":143},{"machine":"crafting_table","chunk":3,"index":144},{"machine":"crafting_table","chunk":3,"index":145},{"machine":"crafting_table","chunk":3,"index":146}]}