{"modId":"bartworks","itemName":"gt.bwMetaGeneratedstick","metadata":39,"displayName":"Californium Rod","unlocalizedName":"gt.bwMetaGeneratedstick.39","oreDictNames":["stickCalifornium"],"id":"bartworks:gt.bwMetaGeneratedstick:39","recipesAsOutput":[{"machine":"crafting_table","chunk":69,"index":490},{"machine":"crafting_table","chunk":85,"index":143},{"machine":"gt.recipe.extruder","chunk":0,"index":26},{"machine":"gt.recipe.fluidsolidifier","chunk":54,"index":143},{"machine":"gt.recipe.lathe","chunk":0,"index":49}],"recipesAsInput":[{"machine":"bw.recipe.radhatch","chunk":0,"index":20},{"machine":"crafting_table","chunk":30,"index":355},{"machine":"crafting_table","chunk":30,"index":355},{"machine":"crafting_table","chunk":30,"index":358},{"machine":"crafting_table","chunk":30,"index":358},{"machine":"crafting_table","chunk":30,"index":360},{"machine":"crafting_table","chunk":30,"index":360},{"machine":"crafting_table","chunk":30,"index":360},{"machine":"crafting_table","chunk":30,"index":361},{"machine":"crafting_table","chunk":30,"index":361},{"machine":"crafting_table","chunk":30,"index":361},{"machine":"crafting_table","chunk":30,"index":361},{"machine":"crafting_table","chunk":30,"index":361},{"machine":"crafting_table","chunk":30,"index":361},{"machine":"crafting_table","chunk":30,"index":362},{"machine":"crafting_table","chunk":66,"index":380},{"machine":"crafting_table","chunk":116,"index":301},{"machine":"crafting_table","chunk":116,"index":301},{"machine":"furnace","chunk":12,"index":372},{"machine":"gt.recipe.alloysmelter","chunk":7,"index":434},{"machine":"gt.recipe.fluidextractor","chunk":21,"index":38},{"machine":"gt.recipe.hammer","chunk":0,"index":402},{"machine":"gt.recipe.macerator","chunk":18,"index":489}]}