{"modId":"gregtech","itemName":"gt.metaitem.02","metadata":13310,"displayName":"Cupronickel Plow Head","unlocalizedName":"gt.metaitem.02.13310","oreDictNames":["toolHeadPlowCupronickel"],"id":"gregtech:gt.metaitem.02:13310","recipesAsOutput":[{"machine":"crafting_table","chunk":67,"index":236}],"recipesAsInput":[{"machine":"crafting_table","chunk":98,"index":395},{"machine":"gt.recipe.arcfurnace","chunk":5,"index":194},{"machine":"gt.recipe.assembler","chunk":13,"index":38},{"machine":"gt.recipe.fluidextractor","chunk":5,"index":320},{"machine":"gt.recipe.macerator","chunk":17,"index":382}]}