{"modId":"gregtech","itemName":"gt.metaitem.02","metadata":4471,"displayName":"Silicone Rubber Hoe Head","unlocalizedName":"gt.metaitem.02.4471","oreDictNames":["toolHeadHoeSilicone","toolHeadHoeAnyRubber","toolHeadHoeAnySyntheticRubber"],"id":"gregtech:gt.metaitem.02:4471","recipesAsOutput":[{"machine":"gt.recipe.extruder","chunk":2,"index":279},{"machine":"gt.recipe.extruder","chunk":10,"index":302}],"recipesAsInput":[{"machine":"crafting_table","chunk":101,"index":20},{"machine":"furnace","chunk":4,"index":488},{"machine":"gt.recipe.alloysmelter","chunk":7,"index":153},{"machine":"gt.recipe.arcfurnace","chunk":5,"index":125},{"machine":"gt.recipe.assembler","chunk":19,"index":435},{"machine":"gt.recipe.fluidextractor","chunk":5,"index":251},{"machine":"gt.recipe.macerator","chunk":17,"index":287}]}