{"modId":"gregtech","itemName":"gt.blockmachines","metadata":11458,"displayName":"4x Trinium Cable","unlocalizedName":"gt.blockmachines.cable.trinium.04","oreDictNames":["cableGt04Trinium"],"id":"gregtech:gt.blockmachines:11458","recipesAsOutput":[{"machine":"gt.recipe.assembler","chunk":9,"index":375},{"machine":"gt.recipe.assembler","chunk":9,"index":376},{"machine":"gt.recipe.assembler","chunk":9,"index":377},{"machine":"gt.recipe.assembler","chunk":9,"index":378},{"machine":"gt.recipe.assembler","chunk":9,"index":379},{"machine":"gt.recipe.assembler","chunk":9,"index":380},{"machine":"gt.recipe.assembler","chunk":9,"index":381},{"machine":"gt.recipe.assembler","chunk":9,"index":382},{"machine":"gt.recipe.assembler","chunk":9,"index":383},{"machine":"gt.recipe.assembler","chunk":9,"index":384},{"machine":"gt.recipe.assembler","chunk":9,"index":385},{"machine":"gt.recipe.assembler","chunk":9,"index":386},{"machine":"gt.recipe.assembler","chunk":9,"index":387},{"machine":"gt.recipe.assembler","chunk":9,"index":388},{"machine":"gt.recipe.assembler","chunk":9,"index":389},{"machine":"gt.recipe.assembler","chunk":9,"index":390},{"machine":"gt.recipe.assembler","chunk":9,"index":391},{"machine":"gt.recipe.assembler","chunk":9,"index":392}],"recipesAsInput":[{"machine":"gt.recipe.arcfurnace","chunk":20,"index":332},{"machine":"gt.recipe.fluidextractor","chunk":21,"index":334},{"machine":"gt.recipe.macerator","chunk":37,"index":143},{"machine":"gt.recipe.unpackager","chunk":0,"index":42}]}