{"modId":"gregtech","itemName":"gt.metaitem.01","metadata":6320,"displayName":"Purified Fluxed Electrum Ore","unlocalizedName":"gt.metaitem.01.6320","oreDictNames":["crushedPurifiedElectrumFlux"],"id":"gregtech:gt.metaitem.01:6320","recipesAsOutput":[{"machine":"gt.recipe.orewasher","chunk":0,"index":454},{"machine":"gt.recipe.orewasher","chunk":0,"index":455},{"machine":"gtpp.recipe.simplewasher","chunk":1,"index":126}],"recipesAsInput":[{"machine":"crafting_table","chunk":86,"index":52},{"machine":"gt.recipe.hammer","chunk":4,"index":32},{"machine":"gt.recipe.macerator","chunk":5,"index":410},{"machine":"gt.recipe.thermalcentrifuge","chunk":0,"index":363}]}