{"modId":"gregtech","itemName":"gt.metaitem.01","metadata":1825,"displayName":"Small Pile of Chromite Dust","unlocalizedName":"gt.metaitem.01.1825","oreDictNames":["dustSmallChromite"],"id":"gregtech:gt.metaitem.01:1825","recipesAsOutput":[{"machine":"crafting_table","chunk":76,"index":377}],"recipesAsInput":[{"machine":"crafting_table","chunk":70,"index":493},{"machine":"crafting_table","chunk":70,"index":493},{"machine":"crafting_table","chunk":70,"index":493},{"machine":"crafting_table","chunk":70,"index":493},{"machine":"gt.recipe.packager","chunk":4,"index":181}]}