{"modId":"gregtech","itemName":"gt.metaitem.02","metadata":24370,"displayName":"Tungstencarbide Spring","unlocalizedName":"gt.metaitem.02.24370","oreDictNames":["springTungstenCarbide"],"id":"gregtech:gt.metaitem.02:24370","recipesAsOutput":[{"machine":"crafting_table","chunk":63,"index":117},{"machine":"gt.recipe.metalbender","chunk":12,"index":134}],"recipesAsInput":[{"machine":"furnace","chunk":8,"index":60},{"machine":"gt.recipe.alloysmelter","chunk":12,"index":445},{"machine":"gt.recipe.arcfurnace","chunk":15,"index":133},{"machine":"gt.recipe.fluidextractor","chunk":16,"index":124},{"machine":"gt.recipe.macerator","chunk":31,"index":197}]}