{"modId":"gregtech","itemName":"gt.blockmachines","metadata":5256,"displayName":"Nonuple Infinity Fluid Pipe","unlocalizedName":"gt.blockmachines.gt_pipe_infinity_nonuple","oreDictNames":["pipeNonupleInfinity"],"id":"gregtech:gt.blockmachines:5256","recipesAsOutput":[{"machine":"gt.recipe.assembler","chunk":11,"index":413}],"recipesAsInput":[{"machine":"gt.recipe.arcfurnace","chunk":17,"index":169},{"machine":"gt.recipe.fakeassemblylineprocess","chunk":0,"index":317},{"machine":"gt.recipe.fakeassemblylineprocess","chunk":0,"index":318},{"machine":"gt.recipe.fakeassemblylineprocess","chunk":0,"index":319},{"machine":"gt.recipe.fakeassemblylineprocess","chunk":0,"index":320},{"machine":"gt.recipe.fakeassemblylineprocess","chunk":0,"index":321},{"machine":"gt.recipe.fakeassemblylineprocess","chunk":0,"index":383},{"machine":"gt.recipe.fluidextractor","chunk":18,"index":68},{"machine":"gt.recipe.macerator","chunk":33,"index":360}]}