{"modId":"gregtech","itemName":"gt.metaitem.01","metadata":27952,"displayName":"Ceruclase Screw","unlocalizedName":"gt.metaitem.01.27952","oreDictNames":["screwCeruclase"],"id":"gregtech:gt.metaitem.01:27952","recipesAsOutput":[{"machine":"crafting_table","chunk":73,"index":0},{"machine":"gt.recipe.fluidsolidifier","chunk":62,"index":206},{"machine":"gt.recipe.lathe","chunk":1,"index":312}],"recipesAsInput":[{"machine":"crafting_table","chunk":35,"index":454},{"machine":"crafting_table","chunk":35,"index":454},{"machine":"crafting_table","chunk":47,"index":42},{"machine":"crafting_table","chunk":59,"index":74},{"machine":"crafting_table","chunk":59,"index":76},{"machine":"crafting_table","chunk":94,"index":225},{"machine":"furnace","chunk":3,"index":455},{"machine":"gt.recipe.alloysmelter","chunk":11,"index":355},{"machine":"gt.recipe.arcfurnace","chunk":13,"index":80},{"machine":"gt.recipe.assembler","chunk":15,"index":147},{"machine":"gt.recipe.fluidextractor","chunk":14,"index":21},{"machine":"gt.recipe.macerator","chunk":28,"index":268},{"machine":"gt.recipe.press","chunk":0,"index":144}]}