{"modId":"gregtech","itemName":"gt.metaitem.02","metadata":21599,"displayName":"Polybenzimidazole Rotor","unlocalizedName":"gt.metaitem.02.21599","oreDictNames":["rotorPolybenzimidazole"],"id":"gregtech:gt.metaitem.02:21599","recipesAsOutput":[{"machine":"crafting_table","chunk":60,"index":357},{"machine":"gt.recipe.assembler","chunk":23,"index":305},{"machine":"gt.recipe.assembler","chunk":23,"index":306},{"machine":"gt.recipe.assembler","chunk":23,"index":307},{"machine":"gt.recipe.extruder","chunk":10,"index":138},{"machine":"gt.recipe.fluidsolidifier","chunk":63,"index":317}],"recipesAsInput":[{"machine":"furnace","chunk":5,"index":99},{"machine":"gt.recipe.alloysmelter","chunk":12,"index":358},{"machine":"gt.recipe.arcfurnace","chunk":14,"index":493},{"machine":"gt.recipe.fluidextractor","chunk":15,"index":473},{"machine":"gt.recipe.macerator","chunk":30,"index":488}]}