{"modId":"gregtech","itemName":"gt.metaitem.01","metadata":20359,"displayName":"Quadruple Niobium Nitride Plate","unlocalizedName":"gt.metaitem.01.20359","oreDictNames":["plateQuadrupleNiobiumNitride"],"id":"gregtech:gt.metaitem.01:20359","recipesAsOutput":[{"machine":"crafting_table","chunk":78,"index":163},{"machine":"crafting_table","chunk":92,"index":448},{"machine":"gt.recipe.metalbender","chunk":1,"index":41},{"machine":"gt.recipe.metalbender","chunk":1,"index":274},{"machine":"gt.recipe.metalbender","chunk":3,"index":22},{"machine":"gt.recipe.metalbender","chunk":4,"index":99},{"machine":"gt.recipe.metalbender","chunk":10,"index":143}],"recipesAsInput":[{"machine":"crafting_table","chunk":82,"index":135},{"machine":"gt.recipe.arcfurnace","chunk":12,"index":390},{"machine":"gt.recipe.fluidextractor","chunk":13,"index":312},{"machine":"gt.recipe.macerator","chunk":28,"index":1}]}