{"modId":"gregtech","itemName":"gt.metaitem.01","metadata":9408,"displayName":"Vivid Alloy Nugget","unlocalizedName":"gt.metaitem.01.9408","oreDictNames":["nuggetVividAlloy"],"id":"gregtech:gt.metaitem.01:9408","recipesAsOutput":[{"machine":"crafting_table","chunk":83,"index":484},{"machine":"furnace","chunk":0,"index":449},{"machine":"furnace","chunk":1,"index":58},{"machine":"furnace","chunk":2,"index":108},{"machine":"furnace","chunk":3,"index":159},{"machine":"furnace","chunk":3,"index":279},{"machine":"furnace","chunk":4,"index":226},{"machine":"furnace","chunk":6,"index":14},{"machine":"furnace","chunk":7,"index":50},{"machine":"furnace","chunk":7,"index":151},{"machine":"gt.recipe.alloysmelter","chunk":4,"index":48},{"machine":"gt.recipe.alloysmelter","chunk":9,"index":114},{"machine":"gt.recipe.alloysmelter","chunk":9,"index":190},{"machine":"gt.recipe.alloysmelter","chunk":9,"index":373},{"machine":"gt.recipe.alloysmelter","chunk":10,"index":166},{"machine":"gt.recipe.alloysmelter","chunk":10,"index":269},{"machine":"gt.recipe.alloysmelter","chunk":10,"index":329},{"machine":"gt.recipe.alloysmelter","chunk":11,"index":461},{"machine":"gt.recipe.alloysmelter","chunk":12,"index":118},{"machine":"gt.recipe.alloysmelter","chunk":12,"index":211},{"machine":"gt.recipe.arcfurnace","chunk":6,"index":173},{"machine":"gt.recipe.arcfurnace","chunk":8,"index":334},{"machine":"gt.recipe.arcfurnace","chunk":8,"index":456},{"machine":"gt.recipe.arcfurnace","chunk":9,"index":264},{"machine":"gt.recipe.arcfurnace","chunk":10,"index":298},{"machine":"gt.recipe.arcfurnace","chunk":10,"index":488},{"machine":"gt.recipe.arcfurnace","chunk":11,"index":110},{"machine":"gt.recipe.arcfurnace","chunk":13,"index":280},{"machine":"gt.recipe.arcfurnace","chunk":14,"index":93},{"machine":"gt.recipe.arcfurnace","chunk":14,"index":246},{"machine":"gt.recipe.fluidsolidifier","chunk":63,"index":442}],"recipesAsInput":[{"machine":"crafting_table","chunk":72,"index":64},{"machine":"crafting_table","chunk":72,"index":64},{"machine":"gt.recipe.alloysmelter","chunk":4,"index":47},{"machine":"gt.recipe.fluidextractor","chunk":22,"index":498},{"machine":"gt.recipe.lathe","chunk":0,"index":455},{"machine":"gt.recipe.macerator","chunk":38,"index":161}]}