{"modId":"gregtech","itemName":"gt.blockmachines","metadata":11105,"displayName":"Elite World Accelerator","unlocalizedName":"gt.blockmachines.basicmachine.accelerator.tier.06","id":"gregtech:gt.blockmachines:11105","recipesAsOutput":[{"machine":"crafting_table","chunk":29,"index":142},{"machine":"gt.recipe.assembler","chunk":4,"index":432}],"recipesAsInput":[{"machine":"gt.recipe.arcfurnace","chunk":19,"index":287},{"machine":"gt.recipe.assembler","chunk":0,"index":440},{"machine":"gt.recipe.macerator","chunk":36,"index":123},{"machine":"thaumcraft_infusion_altar","chunk":3,"index":181},{"machine":"thaumcraft_infusion_altar","chunk":3,"index":181}]}