{"modId":"gregtech","itemName":"gt.metaitem.02","metadata":11302,"displayName":"Invar Universal Spade Head","unlocalizedName":"gt.metaitem.02.11302","oreDictNames":["toolHeadUniversalSpadeInvar"],"id":"gregtech:gt.metaitem.02:11302","recipesAsOutput":[{"machine":"crafting_table","chunk":90,"index":277}],"recipesAsInput":[{"machine":"crafting_table","chunk":94,"index":436},{"machine":"furnace","chunk":7,"index":175},{"machine":"gt.recipe.alloysmelter","chunk":11,"index":161},{"machine":"gt.recipe.arcfurnace","chunk":12,"index":207},{"machine":"gt.recipe.assembler","chunk":22,"index":426},{"machine":"gt.recipe.fluidextractor","chunk":13,"index":123},{"machine":"gt.recipe.macerator","chunk":27,"index":261}]}