{"modId":"gregtech","itemName":"gt.metaitem.01","metadata":22489,"displayName":"Dense Vulcanite Plate","unlocalizedName":"gt.metaitem.01.22489","oreDictNames":["plateDenseVulcanite"],"id":"gregtech:gt.metaitem.01:22489","recipesAsOutput":[{"machine":"gt.recipe.metalbender","chunk":4,"index":86},{"machine":"gt.recipe.metalbender","chunk":6,"index":259},{"machine":"gt.recipe.metalbender","chunk":8,"index":363},{"machine":"gt.recipe.metalbender","chunk":9,"index":441}],"recipesAsInput":[{"machine":"gt.recipe.arcfurnace","chunk":10,"index":261},{"machine":"gt.recipe.fluidextractor","chunk":11,"index":85},{"machine":"gt.recipe.macerator","chunk":24,"index":459}]}