{"modId":"gregtech","itemName":"gt.metaitem.01","metadata":17384,"displayName":"Galgadorian Plate","unlocalizedName":"gt.metaitem.01.17384","oreDictNames":["plateGalgadorian"],"id":"gregtech:gt.metaitem.01:17384","recipesAsOutput":[{"machine":"crafting_table","chunk":84,"index":308},{"machine":"crafting_table","chunk":91,"index":8},{"machine":"gt.recipe.alloysmelter","chunk":2,"index":100},{"machine":"gt.recipe.cuttingsaw","chunk":7,"index":334},{"machine":"gt.recipe.cuttingsaw","chunk":7,"index":335},{"machine":"gt.recipe.cuttingsaw","chunk":7,"index":336},{"machine":"gt.recipe.extruder","chunk":4,"index":112},{"machine":"gt.recipe.fluidsolidifier","chunk":64,"index":370},{"machine":"gt.recipe.hammer","chunk":3,"index":289},{"machine":"gt.recipe.metalbender","chunk":4,"index":41}],"recipesAsInput":[{"machine":"crafting_table","chunk":25,"index":12},{"machine":"crafting_table","chunk":25,"index":12},{"machine":"crafting_table","chunk":25,"index":13},{"machine":"crafting_table","chunk":25,"index":13},{"machine":"crafting_table","chunk":25,"index":14},{"machine":"crafting_table","chunk":25,"index":14},{"machine":"crafting_table","chunk":33,"index":279},{"machine":"crafting_table","chunk":33,"index":279},{"machine":"crafting_table","chunk":33,"index":280},{"machine":"crafting_table","chunk":33,"index":280},{"machine":"crafting_table","chunk":33,"index":281},{"machine":"crafting_table","chunk":33,"index":281},{"machine":"crafting_table","chunk":36,"index":204},{"machine":"crafting_table","chunk":36,"index":204},{"machine":"crafting_table","chunk":36,"index":225},{"machine":"crafting_table","chunk":36,"index":225},{"machine":"crafting_table","chunk":36,"index":225},{"machine":"crafting_table","chunk":36,"index":226},{"machine":"crafting_table","chunk":36,"index":226},{"machine":"crafting_table","chunk":36,"index":226},{"machine":"crafting_table","chunk":36,"index":227},{"machine":"crafting_table","chunk":36,"index":227},{"machine":"crafting_table","chunk":36,"index":227},{"machine":"crafting_table","chunk":36,"index":228},{"machine":"crafting_table","chunk":36,"index":228},{"machine":"crafting_table","chunk":36,"index":228},{"machine":"crafting_table","chunk":36,"index":229},{"machine":"crafting_table","chunk":36,"index":229},{"machine":"crafting_table","chunk":36,"index":229},{"machine":"crafting_table","chunk":36,"index":230},{"machine":"crafting_table","chunk":36,"index":230},{"machine":"crafting_table","chunk":36,"index":230},{"machine":"crafting_table","chunk":36,"index":231},{"machine":"crafting_table","chunk":36,"index":231},{"machine":"crafting_table","chunk":36,"index":231},{"machine":"crafting_table","chunk":36,"index":232},{"machine":"crafting_table","chunk":36,"index":232},{"machine":"crafting_table","chunk":36,"index":232},{"machine":"crafting_table","chunk":36,"index":233},{"machine":"crafting_table","chunk":36,"index":233},{"machine":"crafting_table","chunk":36,"index":233},{"machine":"crafting_table","chunk":38,"index":61},{"machine":"crafting_table","chunk":38,"index":61},{"machine":"crafting_table","chunk":38,"index":61},{"machine":"crafting_table","chunk":38,"index":61},{"machine":"crafting_table","chunk":47,"index":468},{"machine":"crafting_table","chunk":47,"index":468},{"machine":"crafting_table","chunk":47,"index":468},{"machine":"crafting_table","chunk":47,"index":468},{"machine":"crafting_table","chunk":48,"index":187},{"machine":"crafting_table","chunk":48,"index":187},{"machine":"crafting_table","chunk":48,"index":187},{"machine":"crafting_table","chunk":48,"index":187},{"machine":"crafting_table","chunk":49,"index":90},{"machine":"crafting_table","chunk":51,"index":235},{"machine":"crafting_table","chunk":51,"index":235},{"machine":"crafting_table","chunk":51,"index":235},{"machine":"crafting_table","chunk":51,"index":235},{"machine":"crafting_table","chunk":52,"index":351},{"machine":"crafting_table","chunk":52,"index":351},{"machine":"crafting_table","chunk":52,"index":351},{"machine":"crafting_table","chunk":52,"index":351},{"machine":"crafting_table","chunk":56,"index":82},{"machine":"crafting_table","chunk":56,"index":82},{"machine":"crafting_table","chunk":57,"index":430},{"machine":"crafting_table","chunk":57,"index":430},{"machine":"crafting_table","chunk":57,"index":430},{"machine":"crafting_table","chunk":57,"index":432},{"machine":"crafting_table","chunk":57,"index":432},{"machine":"crafting_table","chunk":57,"index":432},{"machine":"crafting_table","chunk":57,"index":432},{"machine":"crafting_table","chunk":57,"index":433},{"machine":"crafting_table","chunk":57,"index":433},{"machine":"crafting_table","chunk":57,"index":433},{"machine":"crafting_table","chunk":57,"index":433},{"machine":"crafting_table","chunk":57,"index":437},{"machine":"crafting_table","chunk":67,"index":1},{"machine":"crafting_table","chunk":67,"index":194},{"machine":"crafting_table","chunk":67,"index":194},{"machine":"crafting_table","chunk":67,"index":194},{"machine":"crafting_table","chunk":67,"index":194},{"machine":"crafting_table","chunk":67,"index":344},{"machine":"crafting_table","chunk":67,"index":344},{"machine":"crafting_table","chunk":68,"index":146},{"machine":"crafting_table","chunk":68,"index":146},{"machine":"crafting_table","chunk":68,"index":444},{"machine":"crafting_table","chunk":68,"index":444},{"machine":"crafting_table","chunk":68,"index":467},{"machine":"crafting_table","chunk":69,"index":132},{"machine":"crafting_table","chunk":78,"index":414},{"machine":"crafting_table","chunk":79,"index":435},{"machine":"crafting_table","chunk":79,"index":435},{"machine":"crafting_table","chunk":80,"index":129},{"machine":"crafting_table","chunk":80,"index":180},{"machine":"crafting_table","chunk":80,"index":181},{"machine":"crafting_table","chunk":80,"index":259},{"machine":"crafting_table","chunk":80,"index":259},{"machine":"crafting_table","chunk":81,"index":224},{"machine":"crafting_table","chunk":83,"index":164},{"machine":"crafting_table","chunk":91,"index":7},{"machine":"crafting_table","chunk":91,"index":488},{"machine":"crafting_table","chunk":91,"index":488},{"machine":"crafting_table","chunk":91,"index":488},{"machine":"crafting_table","chunk":91,"index":488},{"machine":"crafting_table","chunk":91,"index":488},{"machine":"crafting_table","chunk":93,"index":112},{"machine":"crafting_table","chunk":93,"index":112},{"machine":"crafting_table","chunk":93,"index":112},{"machine":"crafting_table","chunk":93,"index":112},{"machine":"crafting_table","chunk":94,"index":106},{"machine":"crafting_table","chunk":94,"index":106},{"machine":"crafting_table","chunk":94,"index":106},{"machine":"furnace","chunk":1,"index":206},{"machine":"gt.recipe.alloysmelter","chunk":11,"index":384},{"machine":"gt.recipe.assembler","chunk":16,"index":226},{"machine":"gt.recipe.assembler","chunk":16,"index":227},{"machine":"gt.recipe.assembler","chunk":16,"index":228},{"machine":"gt.recipe.assembler","chunk":28,"index":415},{"machine":"gt.recipe.compressor","chunk":0,"index":466},{"machine":"gt.recipe.cuttingsaw","chunk":7,"index":262},{"machine":"gt.recipe.cuttingsaw","chunk":7,"index":263},{"machine":"gt.recipe.cuttingsaw","chunk":7,"index":264},{"machine":"gt.recipe.fluidextractor","chunk":14,"index":78},{"machine":"gt.recipe.macerator","chunk":28,"index":339},{"machine":"gt.recipe.metalbender","chunk":2,"index":202},{"machine":"gt.recipe.metalbender","chunk":4,"index":204},{"machine":"gt.recipe.metalbender","chunk":4,"index":211},{"machine":"gt.recipe.metalbender","chunk":5,"index":47},{"machine":"gt.recipe.metalbender","chunk":7,"index":144},{"machine":"gt.recipe.metalbender","chunk":10,"index":209}]}