{"modId":"gregtech","itemName":"gt.metaitem.02","metadata":24355,"displayName":"Magnetic Steel Spring","unlocalizedName":"gt.metaitem.02.24355","oreDictNames":["springSteelMagnetic"],"id":"gregtech:gt.metaitem.02:24355","recipesAsOutput":[{"machine":"crafting_table","chunk":41,"index":164},{"machine":"gt.recipe.metalbender","chunk":3,"index":318},{"machine":"gt.recipe.polarizer","chunk":0,"index":257}],"recipesAsInput":[{"machine":"furnace","chunk":8,"index":43},{"machine":"gt.recipe.alloysmelter","chunk":9,"index":82},{"machine":"gt.recipe.arcfurnace","chunk":8,"index":271},{"machine":"gt.recipe.fluidextractor","chunk":9,"index":29},{"machine":"gt.recipe.macerator","chunk":22,"index":57}]}