{"modId":"gregtech","itemName":"gt.metaitem.02","metadata":22202,"displayName":"Long Terrasteel Rod","unlocalizedName":"gt.metaitem.02.22202","oreDictNames":["stickLongTerrasteel"],"id":"gregtech:gt.metaitem.02:22202","recipesAsOutput":[{"machine":"crafting_table","chunk":83,"index":227},{"machine":"gt.recipe.fluidsolidifier","chunk":62,"index":484},{"machine":"gt.recipe.hammer","chunk":5,"index":333}],"recipesAsInput":[{"machine":"crafting_table","chunk":33,"index":384},{"machine":"crafting_table","chunk":33,"index":385},{"machine":"crafting_table","chunk":33,"index":386},{"machine":"crafting_table","chunk":48,"index":301},{"machine":"crafting_table","chunk":48,"index":302},{"machine":"crafting_table","chunk":48,"index":303},{"machine":"crafting_table","chunk":49,"index":88},{"machine":"crafting_table","chunk":56,"index":63},{"machine":"crafting_table","chunk":56,"index":64},{"machine":"crafting_table","chunk":56,"index":65},{"machine":"crafting_table","chunk":56,"index":66},{"machine":"crafting_table","chunk":56,"index":67},{"machine":"crafting_table","chunk":56,"index":68},{"machine":"crafting_table","chunk":56,"index":69},{"machine":"crafting_table","chunk":56,"index":70},{"machine":"crafting_table","chunk":56,"index":71},{"machine":"crafting_table","chunk":59,"index":105},{"machine":"crafting_table","chunk":59,"index":105},{"machine":"crafting_table","chunk":89,"index":156},{"machine":"furnace","chunk":5,"index":298},{"machine":"gt.recipe.alloysmelter","chunk":5,"index":334},{"machine":"gt.recipe.cuttingsaw","chunk":13,"index":169},{"machine":"gt.recipe.cuttingsaw","chunk":13,"index":170},{"machine":"gt.recipe.cuttingsaw","chunk":13,"index":171},{"machine":"gt.recipe.fluidextractor","chunk":2,"index":194},{"machine":"gt.recipe.macerator","chunk":13,"index":268},{"machine":"gt.recipe.metalbender","chunk":10,"index":306}]}