{"modId":"gregtech","itemName":"gt.metaitem.02","metadata":18542,"displayName":"Terra Casing","unlocalizedName":"gt.metaitem.02.18542","oreDictNames":["itemCasingInfusedEarth"],"id":"gregtech:gt.metaitem.02:18542","recipesAsOutput":[{"machine":"gt.recipe.cuttingsaw","chunk":11,"index":494},{"machine":"gt.recipe.cuttingsaw","chunk":11,"index":495},{"machine":"gt.recipe.cuttingsaw","chunk":11,"index":496}],"recipesAsInput":[{"machine":"gt.recipe.arcfurnace","chunk":5,"index":313},{"machine":"gt.recipe.macerator","chunk":18,"index":39}]}